adsrxn/__init__.py
adsrxn/simsep.py
adsrxn/simsto.py
adsrxn-0.0.9.dist-info/METADATA
adsrxn-0.0.9.dist-info/WHEEL
adsrxn-0.0.9.dist-info/top_level.txt
adsrxn-0.0.9.dist-info/RECORD
